todocli/__init__.py
todocli/category_manager.py
py_todo_cli-0.1.5.dist-info/LICENSE
py_todo_cli-0.1.5.dist-info/METADATA
py_todo_cli-0.1.5.dist-info/WHEEL
py_todo_cli-0.1.5.dist-info/entry_points.txt
py_todo_cli-0.1.5.dist-info/top_level.txt
py_todo_cli-0.1.5.dist-info/RECORD
