Metadata-Version: 2.1
Name: py-todo-cli
Version: 0.1.5
Summary: A module that installs a command line program to manage simple TODO lists
Home-page: https://github.com/Mantaseus/Todo-CLI.git
Author: Mantaseus
License: MIT
Platform: UNKNOWN
Classifier: License :: OSI Approved :: MIT License
Classifier: Operating System :: OS Independent
Requires-Dist: docopt
Requires-Dist: tabulate
